pyunfurl/__init__.py
pyunfurl/example.py
pyunfurl/unfurl.py
pyunfurl/provider_data/__init__.py
pyunfurl/provider_data/custom.py
pyunfurl/provider_data/noembed.py
pyunfurl/provider_data/oembed.py
pyunfurl-0.1.5.dist-info/LICENSE
pyunfurl-0.1.5.dist-info/METADATA
pyunfurl-0.1.5.dist-info/WHEEL
pyunfurl-0.1.5.dist-info/top_level.txt
pyunfurl-0.1.5.dist-info/RECORD
