Metadata-Version: 2.1
Name: pyunfurl
Version: 0.1.5
Summary: library for embedding ('unfurling') content from other sites into your own site
Home-page: https://github.com/lpellis/pyunfurl
Author: Loftie Ellis
Author-email: pyunfurl@unfurl.dev
License: License :: OSI Approved :: MIT License
Platform: UNKNOWN
Classifier: Programming Language :: Python
Classifier: Programming Language :: Python :: 3
Classifier: Operating System :: OS Independent
Requires-Python: >=3.6
Requires-Dist: pyquery
Requires-Dist: requests
Requires-Dist: uritools
Requires-Dist: micawber
